random_fox_image/__init__.py
random_fox_image-0.1.1.dist-info/METADATA
random_fox_image-0.1.1.dist-info/WHEEL
random_fox_image-0.1.1.dist-info/top_level.txt
random_fox_image-0.1.1.dist-info/RECORD
