Metadata-Version: 2.4
Name: random-fox-image
Version: 0.1.1
Summary: A simple library to get random fox images 🦊
Author-email: What-XD <101012824+What-XD@users.noreply.github.com>
License: MIT
Project-URL: Homepage, https://github.com/What-XD/random-fox-image
Requires-Python: >=3.8
Requires-Dist: requests
